flumutdb/__init__.py
flumutdb/flumut_db.sqlite
flumutdb-6.5.dist-info/licenses/LICENSE
flumutdb-6.5.dist-info/METADATA
flumutdb-6.5.dist-info/WHEEL
flumutdb-6.5.dist-info/top_level.txt
flumutdb-6.5.dist-info/RECORD
