Metadata-Version: 2.4
Name: flumutdb
Version: 6.5
Summary: Utility module for FluMut database
Author-email: Edoardo Giussani <egiussani@izsvenezie.it>, Alessandro Sartori <asartori@izsvenezie.it>
License:                     GNU AFFERO GENERAL PUBLIC LICENSE
Project-URL: Home-page, https://github.com/izsvenezie-virology/FluMutDb
Requires-Python: >=3.7
License-File: LICENSE
Dynamic: license-file
